{
  "id": "timeline",
  "type": "SharedSlice",
  "name": "Timeline",
  "description": "Timeline",
  "variations": [
    {
      "id": "default",
      "name": "Default",
      "docURL": "...",
      "version": "initial",
      "description": "Default",
      "imageUrl": "",
      "primary": {
        "title": {
          "type": "Text",
          "config": {
            "label": "Title",
            "placeholder": ""
          }
        },
        "timeline_item": {
          "type": "Group",
          "config": {
            "label": "Timeline Item",
            "repeat": true,
            "fields": {
              "icon": {
                "type": "Image",
                "config": {
                  "label": "Icon",
                  "constraint": {},
                  "thumbnails": []
                }
              },
              "title": {
                "type": "Text",
                "config": {
                  "label": "Title",
                  "placeholder": ""
                }
              },
              "caption": {
                "type": "Text",
                "config": {
                  "label": "Caption",
                  "placeholder": ""
                }
              }
            }
          }
        }
      },
      "items": {}
    }
  ]
}